LICENSE
MANIFEST.in
README.rst
requirements.txt
setup.cfg
setup.py
airwaveapiclient/__init__.py
airwaveapiclient/airwaveapiclient.py
airwaveapiclient/ap_graph.py
airwaveapiclient.egg-info/PKG-INFO
airwaveapiclient.egg-info/SOURCES.txt
airwaveapiclient.egg-info/dependency_links.txt
airwaveapiclient.egg-info/requires.txt
airwaveapiclient.egg-info/top_level.txt
airwaveapiclient/tests/__init__.py
airwaveapiclient/tests/test_airwaveapiclient.py
airwaveapiclient/tests/test_apdetail.py
airwaveapiclient/tests/test_apgraph.py
airwaveapiclient/tests/test_aplist.py
airwaveapiclient/tests/test_report.py
airwaveapiclient/tests/test_utils.py
docs/source/history.rst
docs/source/index.rst
docs/source/installation.rst
docs/source/intro.rst
docs/source/require.rst
docs/source/user_guide/airwaveapiclient.rst
docs/source/user_guide/apdetail.rst
docs/source/user_guide/apgraph.rst
docs/source/user_guide/aplist.rst
docs/source/user_guide/index.rst
docs/source/user_guide/report.rst
docs/source/user_guide/sample_code.rst