Metadata-Version: 1.1
Name: airwaveapiclient
Version: 0.1.11
Summary: Aruba Networks AirWave API Client.
Home-page: https://github.com/mtoshi/airwaveapiclient
Author: Toshikatsu Murakoshi
Author-email: mtoshi.g@gmail.com
License: MIT
Platform: UNKNOWN
Classifier: Development Status :: 3 - Alpha
Classifier: Programming Language :: Python
Classifier: Programming Language :: Python :: 2
Classifier: Programming Language :: Python :: 2.7
Classifier: Programming Language :: Python :: 3
Classifier: Programming Language :: Python :: 3.5
Classifier: Programming Language :: Python :: 3.6
Classifier: Programming Language :: Python :: 3.7
Classifier: Programming Language :: Python :: Implementation :: CPython
Classifier: Programming Language :: Python :: Implementation :: PyPy
Classifier: Topic :: System :: Monitoring
Classifier: Topic :: System :: Networking
